eol_cli/__init__.py
eol_cli/cli.py
eol_cli/api/__init__.py
eol_cli/api/client.py
eol_cli/commands/__init__.py
eol_cli/commands/categories.py
eol_cli/commands/identifiers.py
eol_cli/commands/index.py
eol_cli/commands/products.py
eol_cli/commands/tags.py
eol_cli/formatters/__init__.py
eol_cli/formatters/json_formatter.py
eol_cli/formatters/rich_formatter.py
eol_cli/formatters/xml_formatter.py
eol_cli-0.1.0.dist-info/licenses/LICENSE
eol_cli-0.1.0.dist-info/METADATA
eol_cli-0.1.0.dist-info/WHEEL
eol_cli-0.1.0.dist-info/entry_points.txt
eol_cli-0.1.0.dist-info/top_level.txt
eol_cli-0.1.0.dist-info/RECORD
