Metadata-Version: 2.4
Name: eol-cli
Version: 0.1.0
Summary: CLI tool for endoflife.date API - Check EOL dates and support lifecycles
Author-email: Marc Rivero <mriverolopez@gmail.com>
Maintainer-email: Marc Rivero <mriverolopez@gmail.com>
License: MIT
Project-URL: Homepage, https://github.com/seifreed/eol-cli
Project-URL: Repository, https://github.com/seifreed/eol-cli
Project-URL: Issues, https://github.com/seifreed/eol-cli/issues
Project-URL: Documentation, https://github.com/seifreed/eol-cli#readme
Keywords: eol,endoflife,cli,api,security,pentest
Classifier: Development Status :: 4 - Beta
Classifier: Intended Audience :: Developers
Classifier: Intended Audience :: System Administrators
Classifier: License :: OSI Approved :: MIT License
Classifier: Programming Language :: Python :: 3
Classifier: Programming Language :: Python :: 3.10
Classifier: Programming Language :: Python :: 3.11
Classifier: Programming Language :: Python :: 3.12
Classifier: Programming Language :: Python :: 3.13
Classifier: Programming Language :: Python :: 3.14
Classifier: Topic :: Software Development :: Libraries :: Python Modules
Classifier: Topic :: System :: Systems Administration
Classifier: Topic :: Utilities
Requires-Python: >=3.10
License-File: LICENSE
Requires-Dist: click>=8.1.0
Requires-Dist: rich>=13.0.0
Requires-Dist: requests>=2.31.0
Provides-Extra: dev
Requires-Dist: pytest>=7.0.0; extra == "dev"
Requires-Dist: pytest-cov>=4.0.0; extra == "dev"
Requires-Dist: black>=23.0.0; extra == "dev"
Requires-Dist: ruff>=0.1.0; extra == "dev"
Requires-Dist: mypy>=1.0.0; extra == "dev"
Requires-Dist: build>=1.0.0; extra == "dev"
Requires-Dist: twine>=6.0.0; extra == "dev"
Requires-Dist: pre-commit>=3.0.0; extra == "dev"
Dynamic: license-file
